re_generate/__init__.py
re_generate/cfg_constants.py
re_generate/classes.py
re_generate/generator.py
re_generate/handlers.py
re_generate-0.1.8.dist-info/LICENSE
re_generate-0.1.8.dist-info/METADATA
re_generate-0.1.8.dist-info/WHEEL
re_generate-0.1.8.dist-info/top_level.txt
re_generate-0.1.8.dist-info/RECORD
